{"cameraMode":{"drawMode":0,"name":"Shaded","section":"Shading Mode"},"sceneLighting":true,"audioPlay":false,"sceneViewState":{"m_AlwaysRefresh":false,"showFog":true,"showSkybox":true,"showFlares":true,"showImageEffects":true,"showParticleSystems":true,"showVisualEffectGraphs":true,"m_FxEnabled":true},"in2DMode":false,"pivot":{"x":353.9219970703125,"y":199.36715698242188,"z":76.064453125},"rotation":{"x":-0.09612870216369629,"y":0.02660403773188591,"z":-0.002606217982247472,"w":-0.9950471520423889},"size":490.5842590332031,"orthographic":false}